__init__.py
_version.py
checks.py
flake8_itzma.py
helpers.py
testing_checks.py
tests/__init__.py
tests/test_itzma.py
tests/test_samples/test1.py
tests/test_samples/test2.py
tests/test_samples/test3.py
tests/test_samples/test4.py
tests/test_samples/test5.py
itzma_lint-0.1.2.dist-info/LICENSE
itzma_lint-0.1.2.dist-info/METADATA
itzma_lint-0.1.2.dist-info/WHEEL
itzma_lint-0.1.2.dist-info/top_level.txt
itzma_lint-0.1.2.dist-info/RECORD
