Metadata-Version: 2.1
Name: itzma-lint
Version: 0.1.2
Summary: A customized linter for personal use
Author-email: Tattie Chitrakorn <tc3117@columbia.edu>
License: MIT License
Project-URL: repository, https://github.com/tchitrakorn/itzma-lint
Classifier: Development Status :: 2 - Pre-Alpha
Classifier: Programming Language :: Python :: Implementation :: CPython
Classifier: Programming Language :: Python :: Implementation :: PyPy
Classifier: Programming Language :: Python :: 3.9
Classifier: Programming Language :: Python :: 3.10
Classifier: Programming Language :: Python :: 3.11
Requires-Python: >=3.9
License-File: LICENSE
Requires-Dist: flake8
Requires-Dist: nltk
Requires-Dist: inflection
Provides-Extra: develop
Requires-Dist: pylint ; extra == 'develop'
Requires-Dist: coverage ; extra == 'develop'
Requires-Dist: black ; extra == 'develop'
Requires-Dist: bump2version (>=1.0.0) ; extra == 'develop'
Requires-Dist: check-manifest ; extra == 'develop'
Requires-Dist: mypy ; extra == 'develop'
